agbus-0.5.data/scripts/agbus
utils/__init__.py
utils/byte_range.py
utils/glacier_upload_file.py
agbus-0.5.dist-info/LICENSE
agbus-0.5.dist-info/METADATA
agbus-0.5.dist-info/WHEEL
agbus-0.5.dist-info/top_level.txt
agbus-0.5.dist-info/RECORD
