Metadata-Version: 2.1
Name: agbus
Version: 0.5
Summary: A simplified Amazon Glacier cli, integrated with a database.
Home-page: https://github.com/mah5057/glacier_upload
Author: Matt Hardock
Author-email: mah5057@gmail.com
License: UNKNOWN
Platform: UNKNOWN
Classifier: Programming Language :: Python :: 3
Classifier: License :: OSI Approved :: MIT License
Classifier: Operating System :: OS Independent
Requires-Dist: boto3 (==1.9.50)
Requires-Dist: pymongo (==3.7.2)
